tarka/__init__.py
tarka/asqla/__init__.py
tarka/asqla/alembic.py
tarka/asqla/database.py
tarka/asqla/postgres.py
tarka/asqla/tx.py
tarka/asqla/types.py
tarka/logging/__init__.py
tarka/logging/bootstrap.py
tarka/logging/formatter.py
tarka/logging/handler.py
tarka/logging/hook.py
tarka/logging/level.py
tarka/logging/manager.py
tarka/logging/patch.py
tarka/logging/utility.py
tarka/utility/__init__.py
tarka/utility/aio_sqlite.py
tarka/utility/aio_worker.py
tarka/utility/envvar.py
tarka/utility/importing.py
tarka/utility/sentinel.py
tarka/utility/thread.py
tarka/utility/utf8.py
tarka/utility/algorithm/__init__.py
tarka/utility/algorithm/iter.py
tarka/utility/algorithm/seq.py
tarka/utility/algorithm/traverse.py
tarka/utility/file/__init__.py
tarka/utility/file/name.py
tarka/utility/file/reserve.py
tarka/utility/file/resources.py
tarka/utility/file/safe.py
tarka/utility/serialize/__init__.py
tarka/utility/serialize/deterministic.py
tarka/utility/time/__init__.py
tarka/utility/time/format.py
tarka/utility/time/utc.py
tarka-0.20.0.dist-info/licenses/LICENSE
tarka-0.20.0.dist-info/licenses/NOTICE
tarka-0.20.0.dist-info/METADATA
tarka-0.20.0.dist-info/WHEEL
tarka-0.20.0.dist-info/top_level.txt
tarka-0.20.0.dist-info/RECORD
