Metadata-Version: 2.4
Name: tarka
Version: 0.20.0
Summary: Various things for common use, like a Swiss Army Knife.
Home-page: https://github.com/Traktormaster/tarka
Author: Nándor Mátravölgyi
Author-email: nandor.matra@gmail.com
License: Apache-2.0
Classifier: Programming Language :: Python :: 3
Classifier: Programming Language :: Python :: 3.9
Classifier: Programming Language :: Python :: 3.10
Classifier: Programming Language :: Python :: 3.11
Classifier: Programming Language :: Python :: 3.12
Classifier: Programming Language :: Python :: 3.13
Classifier: Programming Language :: Python :: Implementation :: CPython
Classifier: Intended Audience :: Developers
Requires-Python: >=3.9
License-File: LICENSE
License-File: NOTICE
Requires-Dist: wait_for2>=0.3.1
Provides-Extra: asqla
Requires-Dist: alembic>=1.12; extra == "asqla"
Requires-Dist: sqlalchemy[asyncio]>=2; extra == "asqla"
Dynamic: author
Dynamic: author-email
Dynamic: classifier
Dynamic: description
Dynamic: description-content-type
Dynamic: home-page
Dynamic: license
Dynamic: license-file
Dynamic: provides-extra
Dynamic: requires-dist
Dynamic: requires-python
Dynamic: summary
